README.md
setup.cfg
setup.py
kombu_redis_priority/__init__.py
kombu_redis_priority.egg-info/PKG-INFO
kombu_redis_priority.egg-info/SOURCES.txt
kombu_redis_priority.egg-info/dependency_links.txt
kombu_redis_priority.egg-info/requires.txt
kombu_redis_priority.egg-info/top_level.txt
kombu_redis_priority/scheduling/__init__.py
kombu_redis_priority/scheduling/base.py
kombu_redis_priority/scheduling/prioritized_levels.py
kombu_redis_priority/scheduling/round_robin.py
kombu_redis_priority/scheduling/weighted_prioritized_levels_with_round_robin.py
kombu_redis_priority/transport/__init__.py
kombu_redis_priority/transport/redis_priority_async.py
tests/__init__.py
tests/test_sortedset_transport.py
tests/scheduler/__init__.py
tests/scheduler/test_prioritized_levels.py
tests/scheduler/test_roundrobin.py
tests/scheduler/test_weighted_prioritized_levels_with_round_robin.py
tests/utils/__init__.py
tests/utils/fakeredis_ext.py