Metadata-Version: 1.1
Name: kombu-redis-priority
Version: 0.3.0
Summary: Celery backend using redis SortedSets for priority
Home-page: https://github.com/Captricity/kombu-redis-priority
Author: Captricity
Author-email: webmaster@captricity.com
License: UNKNOWN
Download-URL: https://github.com/Captricity/kombu-redis-priority/tarball/0.3.0
Keywords: redis,sorted-set,kombu
Platform: UNKNOWN
